{
    "bag": "包包",
    "belt": "腰带",
    "blouse": "衬衫",
    "coat": "风衣",
    "dress": "连衣裙",
    "hat": "帽子",
    "jacket": "上衣",
    "jeans": "牛仔裤",
    "jewels": "首饰",
    "polish": "指甲油",
    "pants": "裤子",
    "scarf": "围巾",
    "shoes": "鞋子",
    "shorts": "短裤",
    "skirt": "裙子",
    "sunglasses": "太阳镜",
    "sweater": "羊毛衫",
    "swimwear": "泳衣",
    "t-shirt": "T恤",
    "tank-top": "背心",
    "underwear": "内衣",
    "hairpin": "发卡",
    "pajamas": "睡衣",
    "wedding": "婚纱",
    "sports-wear": "运动服"
}